vnkdj5_utils/__init__.py
vnkdj5_utils/cache.py
vnkdj5_utils-0.1.6.dist-info/METADATA
vnkdj5_utils-0.1.6.dist-info/WHEEL
vnkdj5_utils-0.1.6.dist-info/top_level.txt
vnkdj5_utils-0.1.6.dist-info/RECORD
